KaiyuanPhpKaifaKuangjiaYiiQuanfangweiJiaocheng/README.md
KaiyuanPhpKaifaKuangjiaYiiQuanfangweiJiaocheng/__init__.py
KaiyuanPhpKaifaKuangjiaYiiQuanfangweiJiaocheng/__main__.py
KaiyuanPhpKaifaKuangjiaYiiQuanfangweiJiaocheng/file.pdf
KaiyuanPhpKaifaKuangjiaYiiQuanfangweiJiaocheng/index.html
kaiyuan_php_kaifa_kuangjia_yii_quanfangwei_jiaocheng-2024.3.2.0.dist-info/METADATA
kaiyuan_php_kaifa_kuangjia_yii_quanfangwei_jiaocheng-2024.3.2.0.dist-info/WHEEL
kaiyuan_php_kaifa_kuangjia_yii_quanfangwei_jiaocheng-2024.3.2.0.dist-info/entry_points.txt
kaiyuan_php_kaifa_kuangjia_yii_quanfangwei_jiaocheng-2024.3.2.0.dist-info/top_level.txt
kaiyuan_php_kaifa_kuangjia_yii_quanfangwei_jiaocheng-2024.3.2.0.dist-info/RECORD
